telegram_init_data/__init__.py
telegram_init_data/exceptions.py
telegram_init_data/fastapi.py
telegram_init_data/hash_token.py
telegram_init_data/is_valid.py
telegram_init_data/is_valid3rd.py
telegram_init_data/parse.py
telegram_init_data/sign.py
telegram_init_data/sign_data.py
telegram_init_data/types.py
telegram_init_data/validate.py
telegram_init_data/validate3rd.py
telegram_init_data-1.0.2.dist-info/licenses/LICENSE
telegram_init_data-1.0.2.dist-info/METADATA
telegram_init_data-1.0.2.dist-info/WHEEL
telegram_init_data-1.0.2.dist-info/top_level.txt
telegram_init_data-1.0.2.dist-info/RECORD
