Metadata-Version: 2.4
Name: telegram-init-data
Version: 1.0.2
Summary: Python library for working with Telegram Mini Apps initialization data
Author-email: Imran Gadzhiev <i.gadzhiev.m@gmail.com>
License: MIT
Project-URL: Homepage, https://github.com/telegram-init-data/telegram-init-data-python
Project-URL: Repository, https://github.com/telegram-init-data/telegram-init-data-python
Project-URL: Documentation, https://github.com/telegram-init-data/telegram-init-data-python#readme
Project-URL: Issues, https://github.com/telegram-init-data/telegram-init-data-python/issues
Keywords: telegram,mini-apps,init-data,validation,signature,bot
Classifier: Development Status :: 4 - Beta
Classifier: Intended Audience :: Developers
Classifier: License :: OSI Approved :: MIT License
Classifier: Operating System :: OS Independent
Classifier: Programming Language :: Python :: 3
Classifier: Programming Language :: Python :: 3.8
Classifier: Programming Language :: Python :: 3.9
Classifier: Programming Language :: Python :: 3.10
Classifier: Programming Language :: Python :: 3.11
Classifier: Programming Language :: Python :: 3.12
Classifier: Topic :: Software Development :: Libraries :: Python Modules
Classifier: Topic :: Internet :: WWW/HTTP :: Dynamic Content
Classifier: Topic :: Communications :: Chat
Requires-Python: >=3.8
License-File: LICENSE
Provides-Extra: dev
Requires-Dist: pytest>=7.0; extra == "dev"
Requires-Dist: pytest-cov>=4.0; extra == "dev"
Requires-Dist: black>=22.0; extra == "dev"
Requires-Dist: isort>=5.0; extra == "dev"
Requires-Dist: flake8>=4.0; extra == "dev"
Requires-Dist: mypy>=1.0; extra == "dev"
Provides-Extra: fastapi
Requires-Dist: fastapi>=0.68.0; extra == "fastapi"
Dynamic: license-file
